QuickCite.py
QuickCite-0.0.5.dist-info/LICENSE
QuickCite-0.0.5.dist-info/METADATA
QuickCite-0.0.5.dist-info/WHEEL
QuickCite-0.0.5.dist-info/top_level.txt
QuickCite-0.0.5.dist-info/RECORD
