Metadata-Version: 2.1
Name: QuickCite
Version: 0.0.5
Summary: Pure Python wrapper for the Formatically Citation Website.
Home-page: https://github.com/http-samc/QuickCite
Author: Samarth Chitgopekar
Author-email: sam@chitgopekar.tech
License: UNKNOWN
Platform: UNKNOWN
Requires-Dist: requests (==2.25.1)
